odoo/addons/hr_timesheet_employee_cost_contract/README.rst
odoo/addons/hr_timesheet_employee_cost_contract/__init__.py
odoo/addons/hr_timesheet_employee_cost_contract/__manifest__.py
odoo/addons/hr_timesheet_employee_cost_contract/i18n/es.po
odoo/addons/hr_timesheet_employee_cost_contract/i18n/hr_timesheet_employee_cost_contract.pot
odoo/addons/hr_timesheet_employee_cost_contract/models/__init__.py
odoo/addons/hr_timesheet_employee_cost_contract/models/account_analytic_line.py
odoo/addons/hr_timesheet_employee_cost_contract/models/hr_contract.py
odoo/addons/hr_timesheet_employee_cost_contract/models/hr_employee.py
odoo/addons/hr_timesheet_employee_cost_contract/models/res_company.py
odoo/addons/hr_timesheet_employee_cost_contract/models/res_config.py
odoo/addons/hr_timesheet_employee_cost_contract/models/resource_calendar_leaves.py
odoo/addons/hr_timesheet_employee_cost_contract/readme/CONFIGURE.rst
odoo/addons/hr_timesheet_employee_cost_contract/readme/CONTRIBUTORS.rst
odoo/addons/hr_timesheet_employee_cost_contract/readme/DESCRIPTION.rst
odoo/addons/hr_timesheet_employee_cost_contract/readme/USAGE.rst
odoo/addons/hr_timesheet_employee_cost_contract/static/description/icon.png
odoo/addons/hr_timesheet_employee_cost_contract/static/description/index.html
odoo/addons/hr_timesheet_employee_cost_contract/tests/__init__.py
odoo/addons/hr_timesheet_employee_cost_contract/tests/test_hr_timesheet_employee_cost_contract.py
odoo/addons/hr_timesheet_employee_cost_contract/views/account_analytic_line.xml
odoo/addons/hr_timesheet_employee_cost_contract/views/hr_contract.xml
odoo/addons/hr_timesheet_employee_cost_contract/views/hr_employee.xml
odoo/addons/hr_timesheet_employee_cost_contract/views/res_config_settings.xml
odoo12_addon_hr_timesheet_employee_cost_contract-12.0.1.0.2.dist-info/METADATA
odoo12_addon_hr_timesheet_employee_cost_contract-12.0.1.0.2.dist-info/WHEEL
odoo12_addon_hr_timesheet_employee_cost_contract-12.0.1.0.2.dist-info/top_level.txt
odoo12_addon_hr_timesheet_employee_cost_contract-12.0.1.0.2.dist-info/RECORD
